notel/__init__.py
notel/__main__.py
notel/config.py
notel/modify_info.py
notel/tprint.py
NoTel-0.1a1.dist-info/METADATA
NoTel-0.1a1.dist-info/WHEEL
NoTel-0.1a1.dist-info/entry_points.txt
NoTel-0.1a1.dist-info/top_level.txt
NoTel-0.1a1.dist-info/RECORD
