Metadata-Version: 2.1
Name: NoTel
Version: 0.1a1
Summary: easy telegram notification sender for both python and CLI
Home-page: https://github.com/seyong92/NoTel
Author: Sangeon Yong
Author-email: koragon2@kaist.ac.kr
License: GPL
Platform: UNKNOWN
Requires-Dist: python-telegram-bot (>=11.1.0)
